[
    {
        "sources": [
            "https://anidb.net/anime/6933",
            "https://anilist.co/anime/15137",
            "https://anime-planet.com/anime/entotsuya-peroo",
            "https://anisearch.com/anime/9526",
            "https://kitsu.io/anime/7221",
            "https://myanimelist.net/anime/15137",
            "https://notify.moe/anime/jjEdtKmmg"
        ],
        "title": "Entotsuya Peroo",
        "type": "movie",
        "episodes": 1,
        "status": "finished",
        "picture": "https://cdn.myanimelist.net/images/anime/7/69013.jpg",
        "thumbnail": "https://cdn.myanimelist.net/images/anime/7/69013t.jpg",
        "synonyms": [
            "Chimney Sweep Pero",
            "Chimney shop Perot",
            "Entotsuya Perō",
            "煙突屋ペロー"
        ],
        "relations": [],
        "tags": [
            "adventure",
            "family friendly",
            "fantasy",
            "kids",
            "puppetry",
            "thriller",
            "war"
        ],
        "date": {
            "season": "spring",
            "year": 1930
        }
    },
    {
        "sources": [
            "https://anidb.net/anime/6843",
            "https://anilist.co/anime/106927",
            "https://anime-planet.com/anime/osekisho",
            "https://anisearch.com/anime/10360",
            "https://kitsu.io/anime/40745",
            "https://myanimelist.net/anime/35390",
            "https://notify.moe/anime/aMqv2Fmig"
        ],
        "title": "Osekisho",
        "type": "movie",
        "episodes": 1,
        "status": "finished",
        "picture": "https://cdn.myanimelist.net/images/anime/9/85241.jpg",
        "thumbnail": "https://cdn.myanimelist.net/images/anime/9/85241t.jpg",
        "synonyms": [
            "At the Border Checkpoint",
            "Official Residence",
            "Osekicho",
            "The Inspection Station",
            "お関所"
        ],
        "relations": [],
        "tags": [
            "black and white",
            "dancing",
            "indefinite",
            "kids",
            "no dialogue",
            "shorts",
            "swordplay"
        ],
        "date": {
            "season": "spring",
            "year": 1930
        }
    }
]